aws_sns_sqs_adapter/__init__.py
aws_sns_sqs_adapter/apps.py
aws_sns_sqs_adapter/django_settings.py
aws_sns_sqs_adapter/management/__init__.py
aws_sns_sqs_adapter/management/commands/__init__.py
aws_sns_sqs_adapter/management/commands/init_sns_sqs.py
aws_sns_sqs_adapter/publisher/__init__.py
aws_sns_sqs_adapter/publisher/aws_sns_topic_publisher.py
tests/__init__.py
tests/conftest.py
tests/aws_sns_sqs_adapter/__init__.py
tests/aws_sns_sqs_adapter/test_app_loading.py
tests/aws_sns_sqs_adapter/publisher/__init__.py
tests/aws_sns_sqs_adapter/publisher/test_aws_sns_topic_publisher.py
herbie_aws_sns_sqs_adapter-1.0b1.dist-info/LICENSE
herbie_aws_sns_sqs_adapter-1.0b1.dist-info/METADATA
herbie_aws_sns_sqs_adapter-1.0b1.dist-info/WHEEL
herbie_aws_sns_sqs_adapter-1.0b1.dist-info/top_level.txt
herbie_aws_sns_sqs_adapter-1.0b1.dist-info/RECORD
