Metadata-Version: 2.1
Name: herbie-aws-sns-sqs-adapter
Version: 1.0b1
Summary: Herbie Adapter for messaging publishing to AWS SNS/SQS
Home-page: https://github.com/herbie/aws-sns-sqs-adapter
Author: Project A Services GmbH & Co. KG
Author-email: herbie@project-a.com
License: MIT
Platform: UNKNOWN
Classifier: Programming Language :: Python :: 3.6
Classifier: Programming Language :: Python :: 3.7
Classifier: Programming Language :: Python :: 3.8
Classifier: Framework :: Django :: 3.0
Classifier: Framework :: Django :: 3.1
Classifier: License :: OSI Approved :: MIT License
Classifier: Operating System :: OS Independent
Requires-Python: >=3.6
Requires-Dist: django (<4.0,>=3.0)
Requires-Dist: djangorestframework (<4.0,>=3.11)
Requires-Dist: herbie (==1.0b1)
Requires-Dist: boto3 (<1.15,>=1.14.20)
Provides-Extra: dev
Requires-Dist: twine ; extra == 'dev'
Provides-Extra: tests
Requires-Dist: pytest (<6.0,>=5.4.3) ; extra == 'tests'
Requires-Dist: pytest-django (<4.0,>=3.7.0) ; extra == 'tests'
Requires-Dist: flake8 (>=3.8.0) ; extra == 'tests'
Requires-Dist: black (==19.10b0) ; extra == 'tests'
